vimp/__init__.py
vimp/archive.py
vimp/command.py
vimp/configure.py
vimp/install.py
vimp/log.py
vimp/scripts.py
vimp/util.py
vimp-0.1.4.data/scripts/vimp
vimp-0.1.4.dist-info/DESCRIPTION.rst
vimp-0.1.4.dist-info/METADATA
vimp-0.1.4.dist-info/RECORD
vimp-0.1.4.dist-info/WHEEL
vimp-0.1.4.dist-info/metadata.json
vimp-0.1.4.dist-info/top_level.txt
vimp-0.1.4.dist-info/zip-safe
