Metadata-Version: 2.0
Name: vimp
Version: 0.1.4
Summary: Command line package manager for the vim editor.
Home-page: https://github.com/cslarsen/vimp
Author: Christian Stigen Larsen
Author-email: csl@csl.name
License: https://www.gnu.org/licenses/lgpl-2.1.html
Download-URL: https://github.com/cslarsen/vimp/tarball/0.1.4
Keywords: vim
Platform: unix
Platform: osx
Classifier: Environment :: Console
Classifier: Natural Language :: English
Classifier: Operating System :: MacOS :: MacOS X
Classifier: Operating System :: POSIX
Classifier: Operating System :: Unix
Classifier: Programming Language :: Python
Classifier: Programming Language :: Python :: 2
Classifier: Programming Language :: Python :: 2.6
Classifier: Programming Language :: Python :: 2.7
Classifier: Programming Language :: Python :: 3
Classifier: Programming Language :: Python :: 3.1
Classifier: Programming Language :: Python :: 3.2
Classifier: Programming Language :: Python :: 3.3
Classifier: Programming Language :: Python :: 3.4
Classifier: Programming Language :: Python :: 3.5
Classifier: Programming Language :: Python :: 3.6
